{"title":"健康ランド","Map":4,"NumImpostors":2,"ConfirmEjection":0,"EmergencyMeetings":1,"EmergencyCooldown":20,"DiscussionTime":0,"VotingTime":150,"AnonymousVotes":1,"PlayerSpeed":5,"CrewmateVision":2,"ImpostorVision":6,"KillCooldown":12,"KillDistance":1,"VisualTask":0,"TaskBarUpdates":2,"CommonTasks":2,"LongTasks":3,"ShortTasks":7,"mod_options":[{"id":7,"value":1},{"id":0,"value":0},{"id":300,"value":3},{"id":301,"value":3},{"id":302,"value":0},{"id":303,"value":0},{"id":304,"value":2},{"id":305,"value":2},{"id":400,"value":0},{"id":401,"value":1},{"id":405,"value":1},{"id":406,"value":0},{"id":404,"value":1},{"id":10,"value":0},{"id":12,"value":0},{"id":13,"value":0},{"id":14,"value":0},{"id":11,"value":11},{"id":15,"value":0},{"id":16,"value":0},{"id":17,"value":0},{"id":20,"value":0},{"id":21,"value":11},{"id":22,"value":18},{"id":30,"value":0},{"id":31,"value":11},{"id":32,"value":18},{"id":33,"value":0},{"id":1900,"value":10},{"id":1912,"value":1},{"id":1901,"value":0},{"id":1913,"value":1},{"id":1914,"value":1},{"id":1915,"value":1},{"id":1902,"value":0},{"id":1903,"value":0},{"id":1904,"value":0},{"id":1905,"value":0},{"id":1906,"value":0},{"id":1907,"value":0},{"id":1908,"value":1},{"id":1909,"value":0},{"id":1910,"value":3},{"id":1911,"value":0},{"id":40,"value":0},{"id":41,"value":9},{"id":42,"value":11},{"id":43,"value":1},{"id":230,"value":0},{"id":231,"value":5},{"id":233,"value":4},{"id":232,"value":0},{"id":250,"value":0},{"id":251,"value":3},{"id":252,"value":5},{"id":253,"value":4},{"id":260,"value":0},{"id":261,"value":11},{"id":270,"value":0},{"id":271,"value":11},{"id":272,"value":5},{"id":320,"value":0},{"id":321,"value":5},{"id":322,"value":0},{"id":323,"value":8},{"id":324,"value":1},{"id":325,"value":5},{"id":390,"value":0},{"id":391,"value":11},{"id":392,"value":2},{"id":393,"value":0},{"id":394,"value":1},{"id":395,"value":1},{"id":396,"value":1},{"id":410,"value":0},{"id":411,"value":4},{"id":412,"value":1},{"id":413,"value":8},{"id":414,"value":4},{"id":1000,"value":0},{"id":11000,"value":0},{"id":1002,"value":11},{"id":1003,"value":5},{"id":1004,"value":1},{"id":1005,"value":4},{"id":1006,"value":15},{"id":1007,"value":1},{"id":1008,"value":0},{"id":1010,"value":0},{"id":11010,"value":0},{"id":1012,"value":5},{"id":1013,"value":15},{"id":1014,"value":1},{"id":1070,"value":0},{"id":1079,"value":1},{"id":1071,"value":6},{"id":1072,"value":3},{"id":1073,"value":4},{"id":1074,"value":0},{"id":1076,"value":9},{"id":1077,"value":10},{"id":1078,"value":10},{"id":1030,"value":0},{"id":1031,"value":18},{"id":1032,"value":4},{"id":1033,"value":1},{"id":1034,"value":1},{"id":1035,"value":1},{"id":1036,"value":1},{"id":1037,"value":1},{"id":1050,"value":10},{"id":11050,"value":0},{"id":1052,"value":0},{"id":1053,"value":1},{"id":1054,"value":1},{"id":1055,"value":1},{"id":1056,"value":1},{"id":1057,"value":1},{"id":1080,"value":0},{"id":1081,"value":1},{"id":1082,"value":1},{"id":1083,"value":1},{"id":1020,"value":0},{"id":11020,"value":0},{"id":1021,"value":1},{"id":1022,"value":1},{"id":1023,"value":1},{"id":1024,"value":0},{"id":360,"value":10},{"id":10360,"value":0},{"id":366,"value":1},{"id":369,"value":5},{"id":367,"value":1},{"id":20368,"value":0},{"id":20369,"value":0},{"id":20370,"value":1},{"id":361,"value":1},{"id":362,"value":1},{"id":363,"value":1},{"id":364,"value":0},{"id":365,"value":0},{"id":10370,"value":0},{"id":180,"value":0},{"id":10180,"value":0},{"id":181,"value":3},{"id":50,"value":0},{"id":51,"value":0},{"id":57,"value":0},{"id":52,"value":1},{"id":53,"value":1},{"id":56,"value":1},{"id":55,"value":0},{"id":54,"value":1},{"id":1090,"value":0},{"id":11090,"value":0},{"id":310,"value":0},{"id":311,"value":0},{"id":317,"value":0},{"id":312,"value":1},{"id":313,"value":1},{"id":314,"value":0},{"id":315,"value":1},{"id":316,"value":1},{"id":318,"value":1},{"id":319,"value":1},{"id":150,"value":0},{"id":153,"value":0},{"id":154,"value":1},{"id":151,"value":0},{"id":152,"value":0},{"id":60,"value":0},{"id":61,"value":1},{"id":62,"value":1},{"id":63,"value":0},{"id":290,"value":0},{"id":291,"value":4},{"id":292,"value":3},{"id":293,"value":0},{"id":380,"value":0},{"id":10380,"value":0},{"id":220,"value":0},{"id":221,"value":11},{"id":223,"value":1},{"id":430,"value":0},{"id":224,"value":0},{"id":222,"value":11},{"id":225,"value":0},{"id":226,"value":0},{"id":227,"value":1},{"id":228,"value":1},{"id":229,"value":1},{"id":431,"value":1},{"id":340,"value":0},{"id":341,"value":5},{"id":342,"value":3},{"id":343,"value":1},{"id":344,"value":1},{"id":350,"value":0},{"id":351,"value":1},{"id":352,"value":0},{"id":353,"value":4},{"id":354,"value":3},{"id":355,"value":0},{"id":356,"value":11},{"id":357,"value":5},{"id":70,"value":0},{"id":72,"value":0},{"id":71,"value":0},{"id":73,"value":0},{"id":900,"value":0},{"id":901,"value":3},{"id":902,"value":0},{"id":903,"value":3},{"id":904,"value":4},{"id":905,"value":9},{"id":906,"value":1},{"id":908,"value":1},{"id":1040,"value":0},{"id":11040,"value":0},{"id":101041,"value":1},{"id":101040,"value":0},{"id":1120,"value":0},{"id":11120,"value":0},{"id":1121,"value":9},{"id":1122,"value":0},{"id":1113,"value":0},{"id":1114,"value":1},{"id":910,"value":0},{"id":911,"value":3},{"id":913,"value":4},{"id":914,"value":0},{"id":912,"value":1},{"id":919,"value":1},{"id":916,"value":14},{"id":917,"value":14},{"id":918,"value":1},{"id":940,"value":0},{"id":10940,"value":0},{"id":941,"value":4},{"id":942,"value":0},{"id":943,"value":38},{"id":944,"value":3},{"id":970,"value":0},{"id":971,"value":38},{"id":972,"value":1},{"id":973,"value":0},{"id":974,"value":0},{"id":975,"value":0},{"id":976,"value":0},{"id":977,"value":0},{"id":978,"value":0},{"id":979,"value":0},{"id":1060,"value":0},{"id":1061,"value":2},{"id":1062,"value":4},{"id":1063,"value":1},{"id":1064,"value":1},{"id":1065,"value":1},{"id":1100,"value":0},{"id":1101,"value":2},{"id":1103,"value":7},{"id":1104,"value":12},{"id":1105,"value":1},{"id":21106,"value":1},{"id":21107,"value":2},{"id":21108,"value":3},{"id":1107,"value":2},{"id":1130,"value":0},{"id":1131,"value":0},{"id":1132,"value":29},{"id":1134,"value":2},{"id":1135,"value":0},{"id":1136,"value":0},{"id":1140,"value":0},{"id":11140,"value":0},{"id":1141,"value":3},{"id":1142,"value":4},{"id":1143,"value":4},{"id":1150,"value":0},{"id":1151,"value":9},{"id":1152,"value":1},{"id":960,"value":0},{"id":10960,"value":0},{"id":963,"value":0},{"id":961,"value":6},{"id":962,"value":2},{"id":80,"value":0},{"id":81,"value":0},{"id":90,"value":0},{"id":91,"value":1},{"id":92,"value":1},{"id":93,"value":1},{"id":100,"value":10},{"id":10100,"value":0},{"id":101,"value":11},{"id":103,"value":0},{"id":104,"value":0},{"id":105,"value":1},{"id":102,"value":0},{"id":110,"value":10},{"id":10110,"value":0},{"id":111,"value":5},{"id":112,"value":5},{"id":113,"value":5},{"id":114,"value":11},{"id":115,"value":1},{"id":120,"value":0},{"id":121,"value":0},{"id":122,"value":1},{"id":123,"value":19},{"id":124,"value":0},{"id":125,"value":8},{"id":130,"value":0},{"id":131,"value":11},{"id":132,"value":2},{"id":133,"value":2},{"id":140,"value":0},{"id":143,"value":0},{"id":144,"value":0},{"id":145,"value":0},{"id":146,"value":0},{"id":160,"value":0},{"id":161,"value":0},{"id":163,"value":0},{"id":162,"value":3},{"id":170,"value":0},{"id":171,"value":5},{"id":172,"value":3},{"id":173,"value":0},{"id":174,"value":4},{"id":175,"value":1},{"id":176,"value":1},{"id":200,"value":0},{"id":201,"value":4},{"id":202,"value":0},{"id":203,"value":1},{"id":204,"value":6},{"id":205,"value":1},{"id":210,"value":0},{"id":211,"value":1},{"id":212,"value":0},{"id":213,"value":1},{"id":240,"value":0},{"id":241,"value":0},{"id":242,"value":1},{"id":243,"value":0},{"id":244,"value":0},{"id":280,"value":0},{"id":281,"value":11},{"id":282,"value":6},{"id":283,"value":1},{"id":284,"value":0},{"id":285,"value":3},{"id":286,"value":4},{"id":287,"value":2},{"id":288,"value":1},{"id":330,"value":0},{"id":331,"value":0},{"id":332,"value":0},{"id":333,"value":1},{"id":370,"value":0},{"id":371,"value":5},{"id":372,"value":3},{"id":373,"value":0},{"id":9909,"value":1},{"id":9914,"value":0},{"id":9913,"value":2},{"id":9920,"value":1},{"id":9932,"value":1},{"id":9933,"value":1},{"id":9936,"value":1},{"id":9910,"value":1},{"id":9931,"value":1},{"id":9934,"value":1},{"id":9935,"value":10},{"id":9921,"value":1},{"id":9905,"value":0},{"id":9906,"value":0},{"id":9907,"value":0},{"id":9922,"value":1},{"id":9908,"value":1},{"id":9999,"value":45},{"id":9916,"value":0},{"id":9917,"value":0},{"id":97918,"value":1},{"id":9919,"value":0},{"id":9923,"value":0},{"id":9924,"value":10},{"id":9925,"value":0},{"id":9926,"value":1},{"id":9927,"value":0},{"id":9928,"value":0},{"id":9929,"value":0},{"id":9930,"value":0},{"id":9937,"value":1},{"id":552,"value":0},{"id":9900,"value":0},{"id":9901,"value":0},{"id":9902,"value":3},{"id":9903,"value":0},{"id":9904,"value":0},{"id":3,"value":8},{"id":4,"value":0},{"id":5,"value":0},{"id":550,"value":1},{"id":551,"value":1},{"id":540,"value":0},{"id":520,"value":0},{"id":510,"value":2},{"id":501,"value":1},{"id":502,"value":3},{"id":503,"value":1},{"id":505,"value":0},{"id":506,"value":30},{"id":509,"value":0},{"id":507,"value":1},{"id":508,"value":3},{"id":511,"value":1},{"id":530,"value":0},{"id":8,"value":0},{"id":531,"value":1},{"id":532,"value":1},{"id":533,"value":1},{"id":534,"value":1},{"id":535,"value":1},{"id":504,"value":0},{"id":6,"value":0},{"id":522,"value":0},{"id":521,"value":0}]}